linked_neurons/__init__.py
linked_neurons/linked_neurons.py
linked_neurons-0.1.0.dist-info/DESCRIPTION.rst
linked_neurons-0.1.0.dist-info/METADATA
linked_neurons-0.1.0.dist-info/RECORD
linked_neurons-0.1.0.dist-info/WHEEL
linked_neurons-0.1.0.dist-info/metadata.json
linked_neurons-0.1.0.dist-info/top_level.txt
