Metadata-Version: 2.0
Name: linked-neurons
Version: 0.1.0
Summary: Keras implementation of the article "Solving internal covariate shift in deep learning with linked neurons"
Home-page: https://github.com/blauigris/linked_neurons
Author: Carles R. Riera Molina
Author-email: carlesrieramolina@gmail.com
License: MIT license
Keywords: linked_neurons deep-learning machine-learning neural-networks
Platform: UNKNOWN
Classifier: Development Status :: 2 - Pre-Alpha
Classifier: Intended Audience :: Developers
Classifier: License :: OSI Approved :: MIT License
Classifier: Natural Language :: English
Classifier: Intended Audience :: Science/Research
Classifier: Topic :: Scientific/Engineering :: Artificial Intelligence
Classifier: Programming Language :: Python :: 3
Classifier: Programming Language :: Python :: 3.3
Classifier: Programming Language :: Python :: 3.4
Classifier: Programming Language :: Python :: 3.5
Requires-Python: >=3
Requires-Dist: keras (>=2.0)
Requires-Dist: tensorflow (>=1.4)
